pyannote.parser-0.8-py3.7-nspkg.pth
pyannote/parser/__init__.py
pyannote/parser/_version.py
pyannote/parser/base.py
pyannote/parser/trs.py
pyannote/parser/annotation/__init__.py
pyannote/parser/annotation/base.py
pyannote/parser/annotation/mdtm.py
pyannote/parser/annotation/repere.py
pyannote/parser/annotation/seg.py
pyannote/parser/generic/__init__.py
pyannote/parser/generic/json.py
pyannote/parser/generic/lst.py
pyannote/parser/generic/pkl.py
pyannote/parser/timeline/__init__.py
pyannote/parser/timeline/base.py
pyannote/parser/timeline/uem.py
pyannote.parser-0.8.dist-info/LICENSE
pyannote.parser-0.8.dist-info/METADATA
pyannote.parser-0.8.dist-info/WHEEL
pyannote.parser-0.8.dist-info/entry_points.txt
pyannote.parser-0.8.dist-info/namespace_packages.txt
pyannote.parser-0.8.dist-info/top_level.txt
pyannote.parser-0.8.dist-info/RECORD
