Metadata-Version: 2.1
Name: pyannote.parser
Version: 0.8
Summary: pyannote parsers (deprecated)
Home-page: http://herve.niderb.fr/
Author: Hervé Bredin
Author-email: bredin@limsi.fr
License: UNKNOWN
Platform: UNKNOWN
Classifier: Development Status :: 4 - Beta
Classifier: Intended Audience :: Science/Research
Classifier: License :: OSI Approved :: MIT License
Classifier: Natural Language :: English
Classifier: Programming Language :: Python :: 3.6
Classifier: Programming Language :: Python :: 3.7
Classifier: Programming Language :: Python :: 3.8
Classifier: Topic :: Scientific/Engineering
Requires-Dist: pyannote.core (>=3.3)
Requires-Dist: six (>=1.10.0)
